classdiff/__init__.py
classdiff/classdiff.py
classdiff/diff_object.py
classdiff/examples/classdiff.py
classdiff/utils.py
classdiff-0.5.1.dist-info/METADATA
classdiff-0.5.1.dist-info/WHEEL
classdiff-0.5.1.dist-info/entry_points.txt
classdiff-0.5.1.dist-info/RECORD
