Metadata-Version: 2.3
Name: classdiff
Version: 0.5.1
Summary: Utility to diff classes
License: Apache-2.0
Author: Validio
Author-email: support@validio.io
Requires-Python: >=3.10,<4.0
Classifier: License :: OSI Approved :: Apache Software License
Classifier: Programming Language :: Python :: 3
Classifier: Programming Language :: Python :: 3.10
Classifier: Programming Language :: Python :: 3.11
Classifier: Programming Language :: Python :: 3.12
Classifier: Programming Language :: Python :: 3.13
Requires-Dist: deepdiff (>=6.0.0)
